Time_Corrector/Time_Corrector.py
Time_Corrector/__init__.py
Time_Corrector-1.0.1.dist-info/METADATA
Time_Corrector-1.0.1.dist-info/WHEEL
Time_Corrector-1.0.1.dist-info/top_level.txt
Time_Corrector-1.0.1.dist-info/RECORD
