Metadata-Version: 2.1
Name: Time-Corrector
Version: 1.0.1
Summary: An acquisition time correction tool based on the retention index system for LC-MS data
Author: Wuhan University, Laboratory of Separation Sciences and Bioanalytical Chemistry, Chen Yaoyu
Author-email: <740318407@qq.com>
Keywords: LC-MS,RI system,RT Correct,MS Data
Classifier: Programming Language :: Python :: 3
Classifier: Operating System :: MacOS :: MacOS X
Classifier: Operating System :: Microsoft :: Windows
Requires-Dist: pyopenms
Requires-Dist: pandas
Requires-Dist: progress
Requires-Dist: matplotlib
Requires-Dist: numpy
